.gitignore
CHANGES.txt
README.rst
pyhogan.py
setup.cfg
setup.py
pyhogan.egg-info/PKG-INFO
pyhogan.egg-info/SOURCES.txt
pyhogan.egg-info/dependency_links.txt
pyhogan.egg-info/entry_points.txt
pyhogan.egg-info/not-zip-safe
pyhogan.egg-info/requires.txt
pyhogan.egg-info/top_level.txt
spec/hogan-1.0.5.common.js
spec/mustache_spec.py
spec/_files/ampersand_escape.js
spec/_files/ampersand_escape.mustache
spec/_files/ampersand_escape.txt
spec/_files/apostrophe.js
spec/_files/apostrophe.mustache
spec/_files/apostrophe.txt
spec/_files/array_of_strings.js
spec/_files/array_of_strings.mustache
spec/_files/array_of_strings.txt
spec/_files/backslashes.js
spec/_files/backslashes.mustache
spec/_files/backslashes.txt
spec/_files/bug_11_eating_whitespace.js
spec/_files/bug_11_eating_whitespace.mustache
spec/_files/bug_11_eating_whitespace.txt
spec/_files/changing_delimiters.js
spec/_files/changing_delimiters.mustache
spec/_files/changing_delimiters.txt
spec/_files/comments.js
spec/_files/comments.mustache
spec/_files/comments.txt
spec/_files/complex.js
spec/_files/complex.mustache
spec/_files/complex.txt
spec/_files/context_lookup.js
spec/_files/context_lookup.mustache
spec/_files/context_lookup.txt
spec/_files/delimiters.js
spec/_files/delimiters.mustache
spec/_files/delimiters.txt
spec/_files/disappearing_whitespace.js
spec/_files/disappearing_whitespace.mustache
spec/_files/disappearing_whitespace.txt
spec/_files/dot_notation.js
spec/_files/dot_notation.mustache
spec/_files/dot_notation.txt
spec/_files/double_render.js
spec/_files/double_render.mustache
spec/_files/double_render.txt
spec/_files/empty_list.js
spec/_files/empty_list.mustache
spec/_files/empty_list.txt
spec/_files/empty_sections.js
spec/_files/empty_sections.mustache
spec/_files/empty_sections.txt
spec/_files/empty_string.js
spec/_files/empty_string.mustache
spec/_files/empty_string.txt
spec/_files/empty_template.js
spec/_files/empty_template.mustache
spec/_files/empty_template.txt
spec/_files/error_not_found.js
spec/_files/error_not_found.mustache
spec/_files/error_not_found.txt
spec/_files/escaped.js
spec/_files/escaped.mustache
spec/_files/escaped.txt
spec/_files/higher_order_sections.js
