Metadata-Version: 1.1
Name: pyhogan
Version: 0.2
Summary: Mustache to javascript compiler.
Home-page: https://github.com/fafhrd91/pyhogan/
Author: Nikolay Kim
Author-email: fafhrd91@gmail.com
License: Apache Software License
Platform: UNKNOWN
Classifier: License :: OSI Approved :: Apache Software License
Classifier: Intended Audience :: Developers
Classifier: Programming Language :: Python
Classifier: Programming Language :: Python :: 2.6
Classifier: Programming Language :: Python :: 2.7
Classifier: Programming Language :: Python :: Implementation :: CPython
